quarterback/__init__.py
quarterback/main.py
quarterback-0.1.0.dist-info/WHEEL
quarterback-0.1.0.dist-info/METADATA
quarterback-0.1.0.dist-info/RECORD
